simplesitesystem/__init__.py
simplesitesystem/build.py
simplesitesystem/commands.py
simplesitesystem/dev_server.py
simplesitesystem/extensions.py
simplesitesystem/main.py
simplesitesystem/template_functions.py
simplesitesystem/tools.py
simplesitesystem-0.1.2.dist-info/METADATA
simplesitesystem-0.1.2.dist-info/WHEEL
simplesitesystem-0.1.2.dist-info/entry_points.txt
simplesitesystem-0.1.2.dist-info/licenses/LICENSE
simplesitesystem-0.1.2.dist-info/RECORD
